medikation/__init__.py
medikation/__main__.py
medikation/core/__init__.py
medikation/tests/__init__.py
medikation/tests/test_1984.py
medikation-0.0.0.dev0.dist-info/licenses/LICENSE.txt
medikation-0.0.0.dev0.dist-info/METADATA
medikation-0.0.0.dev0.dist-info/WHEEL
medikation-0.0.0.dev0.dist-info/top_level.txt
medikation-0.0.0.dev0.dist-info/RECORD
